emp_ide_online/__init__.py
emp_ide_online/admin.py
emp_ide_online/apps.py
emp_ide_online/decorators.py
emp_ide_online/models.py
emp_ide_online/rooturls.py
emp_ide_online/settings.py
emp_ide_online/tests.py
emp_ide_online/urls.py
emp_ide_online/views.py
emp_ide_online/wsgi.py
emp_ide_online/static/css/app.a9b6e1cf.css
emp_ide_online/static/css/chunk-329d5946.5e39cfad.css
emp_ide_online/static/css/chunk-vendors.8a6af21e.css
emp_ide_online/static/fonts/MaterialIcons-Regular.012cf6a1.woff
emp_ide_online/static/fonts/MaterialIcons-Regular.570eb838.woff2
emp_ide_online/static/fonts/MaterialIcons-Regular.a37b0c01.ttf
emp_ide_online/static/fonts/MaterialIcons-Regular.e79bfd88.eot
emp_ide_online/static/img/iconfont.573255ce.svg
emp_ide_online/static/js/app.432c990d.js
emp_ide_online/static/js/app.432c990d.js.map
emp_ide_online/static/js/chunk-2d0c0e14.e4f25a38.js
emp_ide_online/static/js/chunk-2d0c0e14.e4f25a38.js.map
emp_ide_online/static/js/chunk-2d0d3720.f764eeca.js
emp_ide_online/static/js/chunk-2d0d3720.f764eeca.js.map
emp_ide_online/static/js/chunk-2d0e64c6.d56af125.js
emp_ide_online/static/js/chunk-2d0e64c6.d56af125.js.map
emp_ide_online/static/js/chunk-2d230ab1.d8b63db6.js
emp_ide_online/static/js/chunk-2d230ab1.d8b63db6.js.map
emp_ide_online/static/js/chunk-329d5946.f788fc45.js
emp_ide_online/static/js/chunk-329d5946.f788fc45.js.map
emp_ide_online/static/js/chunk-vendors.ec36a913.js
emp_ide_online/static/js/chunk-vendors.ec36a913.js.map
emp_ide_online/templates/.gitkeep
emp_ide_online/templates/index.html
emp_ide_online-0.3.0.dist-info/METADATA
emp_ide_online-0.3.0.dist-info/WHEEL
emp_ide_online-0.3.0.dist-info/top_level.txt
emp_ide_online-0.3.0.dist-info/RECORD
